stream_redirect/__init__.py
stream_redirect/complete_redirector.py
stream_redirect/simple_redirector.py
stream_redirect-0.1.2.dist-info/LICENSE
stream_redirect-0.1.2.dist-info/METADATA
stream_redirect-0.1.2.dist-info/WHEEL
stream_redirect-0.1.2.dist-info/top_level.txt
stream_redirect-0.1.2.dist-info/RECORD
