Metadata-Version: 2.1
Name: stream-redirect
Version: 0.1.2
Summary: Collect and redirect stdout and stderr from a python program
Home-page: https://github.com/greg-hellings/stream_redirect
Author: Greg Hellings
Author-email: greg.hellings@gmail.com
License: GPLv3
Platform: UNKNOWN
Classifier: Development Status :: 3 - Alpha
Classifier: Intended Audience :: Developers
Classifier: License :: OSI Approved :: GNU General Public License v3 (GPLv3)
Classifier: Programming Language :: Python
Classifier: Programming Language :: Python :: 2
Classifier: Programming Language :: Python :: 3
Classifier: Topic :: Software Development :: Testing
Requires-Python: >=2.7, !=3.0.*, !=3.1.*, !=3.2.*, !=3.3.*
Requires-Dist: six
